nrkvisual/__init__.py
nrkvisual/main.py
nrkvisual/tkhelper/__init__.py
nrkvisual/visual/__init__.py
nrkvisual/visual/Henry37.xlsx
nrkvisual/visual/plotting.py
nrkvisual-0.1.4.dist-info/WHEEL
nrkvisual-0.1.4.dist-info/METADATA
nrkvisual-0.1.4.dist-info/RECORD
